{
  "id": "Wallet_Pay_Vibe_Prompt_Playbook",
  "title": "Wallet_Pay_Vibe_Prompt_Playbook",
  "description": "Quick Start Mega Prompt",
  "source": "@site/docs/Wallet_Pay_Vibe_Prompt_Playbook.md",
  "sourceDirName": ".",
  "slug": "/Wallet_Pay_Vibe_Prompt_Playbook",
  "permalink": "/openmark/docs/Wallet_Pay_Vibe_Prompt_Playbook",
  "draft": false,
  "unlisted": false,
  "editUrl": "https://github.com/MiaoMiltonMiao/openmark/edit/main/docs/Wallet_Pay_Vibe_Prompt_Playbook.md",
  "tags": [],
  "version": "current",
  "frontMatter": {},
  "sidebar": "docs",
  "previous": {
    "title": "Welcome to OpenMark",
    "permalink": "/openmark/docs/intro"
  }
}